dramatiq_kombu_broker/__init__.py
dramatiq_kombu_broker/_types.py
dramatiq_kombu_broker/broker.py
dramatiq_kombu_broker/connection_holder.py
dramatiq_kombu_broker/consumer.py
dramatiq_kombu_broker/exceptions.py
dramatiq_kombu_broker/pooled_connection_holder.py
dramatiq_kombu_broker/producer.py
dramatiq_kombu_broker/shared_connection_holder.py
dramatiq_kombu_broker/testing.py
dramatiq_kombu_broker/topology.py
dramatiq_kombu_broker-0.3.0.dist-info/METADATA
dramatiq_kombu_broker-0.3.0.dist-info/WHEEL
dramatiq_kombu_broker-0.3.0.dist-info/licenses/LICENSE
dramatiq_kombu_broker-0.3.0.dist-info/RECORD
