Metadata-Version: 2.4
Name: dramatiq-kombu-broker
Version: 0.3.0
Summary: Dramatiq Kombu-based broker
Project-URL: Repository, https://github.com/spumer/dramatiq-kombu-broker
Author-email: spumer <spumer-tm@yandex.ru>
License-File: LICENSE
Requires-Python: <4.0,>=3.10
Requires-Dist: dramatiq<3.0.0,>=1.0.0
Requires-Dist: kombu-pyamqp-threadsafe>=0.6.2
